video_io/__init__.py
video_io/client/__init__.py
video_io/client/core.py
video_io/client/errors.py
video_io/client/utils.py
video_io/config.py
video_io/core.py
video_io/errors.py
video_io/log_retry.py
video_io/utils.py
video_io/video_reader.py
wf_video_io-3.4.3.dist-info/LICENSE
wf_video_io-3.4.3.dist-info/WHEEL
wf_video_io-3.4.3.dist-info/METADATA
wf_video_io-3.4.3.dist-info/RECORD
